draftin_a_flask/__init__.py
draftin_a_flask/draftin_a_flask.py
draftin_a_flask/utils.py
draftin_a_flask-0.2.0.data/scripts/draftican
draftin_a_flask-0.2.0.dist-info/AUTHORS.rst
draftin_a_flask-0.2.0.dist-info/LICENSE
draftin_a_flask-0.2.0.dist-info/METADATA
draftin_a_flask-0.2.0.dist-info/WHEEL
draftin_a_flask-0.2.0.dist-info/top_level.txt
draftin_a_flask-0.2.0.dist-info/RECORD
