Metadata-Version: 2.1
Name: draftin-a-flask
Version: 0.2.0
Summary: A simple Flask server that allows you to publish Pelican blags from http://draftin.com
Home-page: https://github.com/waynew/draftin-a-flask
Author: Wayne Werner
Author-email: waynejwerner@gmail.com
License: BSD
Keywords: draft flask pelican blog publish
Platform: UNKNOWN
Classifier: Development Status :: 2 - Pre-Alpha
Classifier: Intended Audience :: Developers
Classifier: License :: OSI Approved :: BSD License
Classifier: Natural Language :: English
Classifier: Programming Language :: Python :: 2
Classifier: Programming Language :: Python :: 2.7
Classifier: Programming Language :: Python :: 3
Classifier: Programming Language :: Python :: 3.5
Classifier: Programming Language :: Python :: 3.6
Classifier: Programming Language :: Python :: 3.7
Classifier: Programming Language :: Python :: 3.8
Requires-Dist: flask
